[
 {
  "Status": "success",
  "Time": "2025-02-21T00:12:08Z",
  "Name": "package-libsepol2"
 },
 {
  "Status": "stale",
  "Time": "2025-02-19T00:27:11Z",
  "Name": "package-ignition"
 },
 {
  "Status": "success",
  "Time": "2025-02-21T00:14:50Z",
  "Name": "package-aws-kms-pkcs11"
 },
 {
  "Status": "success",
  "Time": "2025-02-21T00:25:40Z",
  "Name": "package-aws-sdk-cpp"
 },
 {
  "Status": "success",
  "Time": "2025-02-21T00:13:43Z",
  "Name": "package-glvd"
 },
 {
  "Status": "success",
  "Time": "2025-02-21T00:04:24Z",
  "Name": "package-onmetal-image"
 },
 {
  "Status": "stale",
  "Time": "2024-03-08T00:15:59Z",
  "Name": "package-syslinux"
 },
 {
  "Status": "success",
  "Time": "2025-02-21T00:29:41Z",
  "Name": "package-fail2ban"
 },
 {
  "Status": "success",
  "Time": "2025-02-21T00:25:31Z",
  "Name": "package-efitools"
 },
 {
  "Status": "success",
  "Time": "2025-02-21T00:12:30Z",
  "Name": "package-openssh"
 },
 {
  "Status": "success",
  "Time": "2025-02-21T00:19:38Z",
  "Name": "package-pam"
 },
 {
  "Status": "success",
  "Time": "2025-02-21T00:26:31Z",
  "Name": "package-xz-utils"
 },
 {
  "Status": "success",
  "Time": "2025-02-21T00:21:33Z",
  "Name": "package-openssl"
 },
 {
  "Status": "success",
  "Time": "2025-02-21T00:08:45Z",
  "Name": "package-golang-github-containers-libhvee"
 },
 {
  "Status": "success",
  "Time": "2025-02-21T00:04:52Z",
  "Name": "package-htop-dev"
 },
 {
  "Status": "success",
  "Time": "2025-02-21T00:13:55Z",
  "Name": "package-python3.13"
 },
 {
  "Status": "stale",
  "Time": "2024-05-08T00:07:58Z",
  "Name": "package-libyang2"
 },
 {
  "Status": "success",
  "Time": "2025-02-21T00:03:18Z",
  "Name": "package-perl"
 },
 {
  "Status": "stale",
  "Time": "2024-03-08T00:21:55Z",
  "Name": "package-tar"
 },
 {
  "Status": "success",
  "Time": "2025-02-21T00:12:27Z",
  "Name": "package-cyrus-sasl2"
 },
 {
  "Status": "success",
  "Time": "2025-02-21T00:16:15Z",
  "Name": "package-oras"
 },
 {
  "Status": "success",
  "Time": "2025-02-21T00:08:34Z",
  "Name": "package-jinja2"
 },
 {
  "Status": "success",
  "Time": "2025-02-21T00:02:05Z",
  "Name": "package-golang-github-checkpoint-restore-go-criu-dev"
 },
 {
  "Status": "success",
  "Time": "2025-02-21T00:29:33Z",
  "Name": "package-libstoragemgmt"
 },
 {
  "Status": "success",
  "Time": "2025-02-21T00:26:33Z",
  "Name": "package-metalbond"
 },
 {
  "Status": "stale",
  "Time": "2025-01-02T00:16:17Z",
  "Name": "package-usr-is-merged"
 },
 {
  "Status": "success",
  "Time": "2025-02-21T00:27:44Z",
  "Name": "package-google-compute-engine-oslogin"
 },
 {
  "Status": "workFlowNotFound",
  "Time": "2025-02-21T07:01:56.487016876Z",
  "Name": "package-policycoreutils"
 },
 {
  "Status": "success",
  "Time": "2025-02-21T00:09:56Z",
  "Name": "package-iproute2"
 },
 {
  "Status": "success",
  "Time": "2025-02-21T00:10:19Z",
  "Name": "package-libxml2"
 },
 {
  "Status": "success",
  "Time": "2025-02-21T00:21:07Z",
  "Name": "package-libpcap"
 },
 {
  "Status": "success",
  "Time": "2025-02-21T00:09:53Z",
  "Name": "package-sbsigntool"
 },
 {
  "Status": "stale",
  "Time": "2025-02-19T00:08:54Z",
  "Name": "package-frr"
 },
 {
  "Status": "success",
  "Time": "2025-02-21T00:17:17Z",
  "Name": "package-curl"
 },
 {
  "Status": "success",
  "Time": "2025-02-21T00:28:00Z",
  "Name": "package-expat"
 },
 {
  "Status": "success",
  "Time": "2025-02-21T00:26:19Z",
  "Name": "package-containerd"
 },
 {
  "Status": "success",
  "Time": "2025-02-21T00:22:10Z",
  "Name": "package-bootloader"
 },
 {
  "Status": "success",
  "Time": "2025-02-21T00:33:50Z",
  "Name": "package-linux"
 },
 {
  "Status": "stale",
  "Time": "2025-02-06T00:17:19Z",
  "Name": "package-sssd"
 },
 {
  "Status": "stale",
  "Time": "2024-05-16T00:11:03Z",
  "Name": "package-cloud-init"
 },
 {
  "Status": "success",
  "Time": "2025-02-21T00:23:07Z",
  "Name": "package-sops"
 },
 {
  "Status": "stale",
  "Time": "2025-01-04T00:19:27Z",
  "Name": "package-uid-wrapper"
 },
 {
  "Status": "success",
  "Time": "2025-02-21T00:26:17Z",
  "Name": "package-gardenlinux-update"
 },
 {
  "Status": "success",
  "Time": "2025-02-21T00:05:36Z",
  "Name": "package-systemd"
 },
 {
  "Status": "success",
  "Time": "2025-02-21T00:27:39Z",
  "Name": "package-gardenlinux-repo-manager"
 },
 {
  "Status": "failure",
  "Time": "2025-01-29T00:14:21Z",
  "Name": "package-python3.11"
 },
 {
  "Status": "stale",
  "Time": "2025-02-11T00:22:22Z",
  "Name": "package-python3.12"
 },
 {
  "Status": "success",
  "Time": "2025-02-21T00:15:46Z",
  "Name": "package-ferm"
 },
 {
  "Status": "stale",
  "Time": "2024-10-11T00:13:42Z",
  "Name": "package-ostree"
 },
 {
  "Status": "success",
  "Time": "2025-02-21T00:03:47Z",
  "Name": "package-deborphan"
 },
 {
  "Status": "success",
  "Time": "2025-02-21T00:20:38Z",
  "Name": "package-runc"
 },
 {
  "Status": "success",
  "Time": "2025-02-21T00:01:16Z",
  "Name": "package-sudosh2"
 },
 {
  "Status": "success",
  "Time": "2025-02-21T00:09:37Z",
  "Name": "package-datefudge"
 },
 {
  "Status": "success",
  "Time": "2025-02-21T00:31:28Z",
  "Name": "package-libguestfs"
 },
 {
  "Status": "success",
  "Time": "2025-02-21T00:17:01Z",
  "Name": "package-gardenlinux-selinux-module"
 },
 {
  "Status": "stale",
  "Time": "2024-07-10T00:03:22Z",
  "Name": "package-open-vm-tools"
 },
 {
  "Status": "success",
  "Time": "2025-02-21T00:03:56Z",
  "Name": "package-golang"
 },
 {
  "Status": "success",
  "Time": "2025-02-21T00:11:16Z",
  "Name": "package-htop"
 },
 {
  "Status": "success",
  "Time": "2025-02-21T00:15:03Z",
  "Name": "package-bind9"
 },
 {
  "Status": "success",
  "Time": "2025-02-21T00:13:12Z",
  "Name": "package-google-guest-agent"
 },
 {
  "Status": "success",
  "Time": "2025-02-21T00:22:36Z",
  "Name": "package-libpam-ssh"
 },
 {
  "Status": "success",
  "Time": "2025-02-21T00:31:10Z",
  "Name": "package-refpolicy"
 },
 {
  "Status": "success",
  "Time": "2025-02-21T00:11:14Z",
  "Name": "package-selinux-basics"
 },
 {
  "Status": "success",
  "Time": "2025-02-21T00:03:43Z",
  "Name": "package-rsync"
 },
 {
  "Status": "failure",
  "Time": "2025-02-03T00:14:49Z",
  "Name": "package-neofetch"
 },
 {
  "Status": "success",
  "Time": "2025-02-21T00:02:45Z",
  "Name": "package-resizefat32"
 },
 {
  "Status": "success",
  "Time": "2025-02-21T00:20:03Z",
  "Name": "package-krb5"
 }
]