[
 {
  "Status": "success",
  "Time": "2025-11-01T00:18:18Z",
  "Name": "package-ignition"
 },
 {
  "Status": "noRunFound",
  "Time": "2025-11-01T07:01:30.875959091Z",
  "Name": "package-open-vm-tools"
 },
 {
  "Status": "success",
  "Time": "2025-11-01T00:22:22Z",
  "Name": "package-libsemanage"
 },
 {
  "Status": "success",
  "Time": "2025-11-01T00:30:44Z",
  "Name": "package-zero-copy-initrd"
 },
 {
  "Status": "success",
  "Time": "2025-11-01T00:04:24Z",
  "Name": "package-libstoragemgmt"
 },
 {
  "Status": "success",
  "Time": "2025-11-01T00:32:39Z",
  "Name": "package-tcpdump"
 },
 {
  "Status": "success",
  "Time": "2025-11-01T00:28:28Z",
  "Name": "package-libgcrypt"
 },
 {
  "Status": "success",
  "Time": "2025-11-01T00:10:49Z",
  "Name": "package-aws-kms-pkcs11"
 },
 {
  "Status": "success",
  "Time": "2025-11-01T00:35:38Z",
  "Name": "package-gardenlinux-repo-manager"
 },
 {
  "Status": "success",
  "Time": "2025-11-01T00:39:42Z",
  "Name": "package-linux"
 },
 {
  "Status": "failure",
  "Time": "2025-03-10T12:46:08Z",
  "Name": "package-efitools"
 },
 {
  "Status": "success",
  "Time": "2025-11-01T00:05:18Z",
  "Name": "package-libguestfs"
 },
 {
  "Status": "success",
  "Time": "2025-11-01T00:12:21Z",
  "Name": "package-bootloader"
 },
 {
  "Status": "success",
  "Time": "2025-11-01T00:22:25Z",
  "Name": "package-deborphan"
 },
 {
  "Status": "success",
  "Time": "2025-11-01T00:09:32Z",
  "Name": "package-jinja2"
 },
 {
  "Status": "success",
  "Time": "2025-11-01T00:12:24Z",
  "Name": "package-google-compute-engine-oslogin"
 },
 {
  "Status": "success",
  "Time": "2025-11-01T00:15:21Z",
  "Name": "package-ovh-debian-cis"
 },
 {
  "Status": "success",
  "Time": "2025-11-01T00:24:11Z",
  "Name": "package-krb5"
 },
 {
  "Status": "success",
  "Time": "2025-11-01T00:12:04Z",
  "Name": "package-sops"
 },
 {
  "Status": "success",
  "Time": "2025-11-01T00:06:47Z",
  "Name": "package-xz-utils"
 },
 {
  "Status": "success",
  "Time": "2025-11-01T00:22:16Z",
  "Name": "package-htop-dev"
 },
 {
  "Status": "success",
  "Time": "2025-11-01T00:16:14Z",
  "Name": "package-edk2-cloud-hypervisor-gl"
 },
 {
  "Status": "success",
  "Time": "2025-11-01T00:11:00Z",
  "Name": "package-golang-github-containers-libhvee"
 },
 {
  "Status": "success",
  "Time": "2025-11-01T00:36:18Z",
  "Name": "package-glvd"
 },
 {
  "Status": "success",
  "Time": "2025-11-01T00:25:16Z",
  "Name": "package-google-guest-agent"
 },
 {
  "Status": "success",
  "Time": "2025-11-01T00:03:19Z",
  "Name": "package-sbsigntool"
 },
 {
  "Status": "success",
  "Time": "2025-11-01T00:08:35Z",
  "Name": "package-gnutls"
 },
 {
  "Status": "success",
  "Time": "2025-11-01T00:38:01Z",
  "Name": "package-gardenlinux-selinux-module"
 },
 {
  "Status": "success",
  "Time": "2025-11-01T00:34:27Z",
  "Name": "package-metalbond"
 },
 {
  "Status": "success",
  "Time": "2025-11-01T00:33:38Z",
  "Name": "package-runc"
 },
 {
  "Status": "stale",
  "Time": "2025-02-11T00:22:22Z",
  "Name": "package-python3.12"
 },
 {
  "Status": "success",
  "Time": "2025-11-01T00:08:02Z",
  "Name": "package-systemd"
 },
 {
  "Status": "success",
  "Time": "2025-11-01T00:34:17Z",
  "Name": "package-aws-sdk-cpp"
 },
 {
  "Status": "success",
  "Time": "2025-11-01T00:33:23Z",
  "Name": "package-onmetal-image"
 },
 {
  "Status": "success",
  "Time": "2025-11-01T00:03:20Z",
  "Name": "package-rsync"
 },
 {
  "Status": "success",
  "Time": "2025-11-01T00:07:51Z",
  "Name": "package-python3.13"
 },
 {
  "Status": "success",
  "Time": "2025-11-01T00:36:25Z",
  "Name": "package-keylime-agent"
 },
 {
  "Status": "success",
  "Time": "2025-11-01T00:17:37Z",
  "Name": "package-cloud-init"
 },
 {
  "Status": "success",
  "Time": "2025-11-01T00:30:43Z",
  "Name": "package-resizefat32"
 },
 {
  "Status": "success",
  "Time": "2025-11-01T00:10:43Z",
  "Name": "package-libpcap"
 },
 {
  "Status": "success",
  "Time": "2025-11-01T00:19:44Z",
  "Name": "package-golang-github-checkpoint-restore-go-criu-dev"
 },
 {
  "Status": "success",
  "Time": "2025-11-01T00:23:23Z",
  "Name": "package-libcap2"
 },
 {
  "Status": "success",
  "Time": "2025-11-01T00:31:13Z",
  "Name": "package-pam"
 },
 {
  "Status": "success",
  "Time": "2025-11-01T00:22:38Z",
  "Name": "package-openssl"
 },
 {
  "Status": "success",
  "Time": "2025-11-01T00:11:15Z",
  "Name": "package-containerd"
 },
 {
  "Status": "stale",
  "Time": "2025-10-20T00:16:12Z",
  "Name": "package-bind9"
 },
 {
  "Status": "success",
  "Time": "2025-11-01T00:01:34Z",
  "Name": "package-google-compute-engine"
 },
 {
  "Status": "success",
  "Time": "2025-11-01T00:29:23Z",
  "Name": "package-cloud-hypervisor-gl"
 },
 {
  "Status": "success",
  "Time": "2025-11-01T00:29:33Z",
  "Name": "package-ffmpeg"
 },
 {
  "Status": "success",
  "Time": "2025-11-01T00:07:51Z",
  "Name": "package-sudosh2"
 },
 {
  "Status": "success",
  "Time": "2025-11-01T00:33:40Z",
  "Name": "package-ferm"
 },
 {
  "Status": "success",
  "Time": "2025-11-01T00:28:02Z",
  "Name": "package-openssh"
 },
 {
  "Status": "success",
  "Time": "2025-11-01T00:35:05Z",
  "Name": "package-oras"
 },
 {
  "Status": "success",
  "Time": "2025-11-01T00:01:59Z",
  "Name": "package-perl"
 },
 {
  "Status": "success",
  "Time": "2025-11-01T00:14:12Z",
  "Name": "package-frr"
 },
 {
  "Status": "failure",
  "Time": "2025-01-29T00:14:21Z",
  "Name": "package-python3.11"
 },
 {
  "Status": "success",
  "Time": "2025-11-01T00:25:06Z",
  "Name": "package-libxml2"
 },
 {
  "Status": "success",
  "Time": "2025-11-01T00:26:33Z",
  "Name": "package-curl"
 },
 {
  "Status": "success",
  "Time": "2025-11-01T00:09:53Z",
  "Name": "package-golang"
 },
 {
  "Status": "success",
  "Time": "2025-11-01T00:21:51Z",
  "Name": "package-datefudge"
 },
 {
  "Status": "success",
  "Time": "2025-11-01T00:33:33Z",
  "Name": "package-expat"
 },
 {
  "Status": "success",
  "Time": "2025-11-01T00:03:12Z",
  "Name": "package-sshguard"
 },
 {
  "Status": "success",
  "Time": "2025-11-01T00:28:28Z",
  "Name": "package-refpolicy"
 },
 {
  "Status": "success",
  "Time": "2025-11-01T00:35:33Z",
  "Name": "package-selinux-basics"
 },
 {
  "Status": "success",
  "Time": "2025-11-01T00:09:30Z",
  "Name": "package-ignition-legacy"
 },
 {
  "Status": "success",
  "Time": "2025-11-01T00:29:33Z",
  "Name": "package-libsepol2"
 },
 {
  "Status": "success",
  "Time": "2025-11-01T00:26:07Z",
  "Name": "package-libvirt"
 },
 {
  "Status": "success",
  "Time": "2025-11-01T00:16:43Z",
  "Name": "package-cyrus-sasl2"
 },
 {
  "Status": "success",
  "Time": "2025-11-01T00:35:13Z",
  "Name": "package-libpam-ssh"
 },
 {
  "Status": "success",
  "Time": "2025-11-01T00:25:22Z",
  "Name": "package-gardenlinux-update"
 },
 {
  "Status": "success",
  "Time": "2025-11-01T00:08:03Z",
  "Name": "package-htop"
 },
 {
  "Status": "success",
  "Time": "2025-11-01T00:29:28Z",
  "Name": "package-iproute2"
 }
]