[
 {
  "Status": "success",
  "Time": "2025-12-29T00:18:00Z",
  "Name": "package-xz-utils"
 },
 {
  "Status": "stale",
  "Time": "2025-12-24T00:21:50Z",
  "Name": "package-libsemanage"
 },
 {
  "Status": "success",
  "Time": "2025-12-29T00:27:42Z",
  "Name": "package-gardenlinux-update"
 },
 {
  "Status": "success",
  "Time": "2025-12-29T00:06:45Z",
  "Name": "package-apt"
 },
 {
  "Status": "success",
  "Time": "2025-12-29T00:23:27Z",
  "Name": "package-cyrus-sasl2"
 },
 {
  "Status": "success",
  "Time": "2025-12-29T00:29:18Z",
  "Name": "package-deborphan"
 },
 {
  "Status": "success",
  "Time": "2025-12-29T00:09:53Z",
  "Name": "package-google-compute-engine-oslogin"
 },
 {
  "Status": "success",
  "Time": "2025-12-29T00:38:13Z",
  "Name": "package-tcpdump"
 },
 {
  "Status": "success",
  "Time": "2025-12-29T00:28:01Z",
  "Name": "package-libvirt"
 },
 {
  "Status": "success",
  "Time": "2025-12-29T00:40:31Z",
  "Name": "package-libstoragemgmt"
 },
 {
  "Status": "success",
  "Time": "2025-12-29T00:33:16Z",
  "Name": "package-metalbond"
 },
 {
  "Status": "success",
  "Time": "2025-12-29T00:28:46Z",
  "Name": "package-sudosh2"
 },
 {
  "Status": "workFlowNotFound",
  "Time": "2025-12-29T07:05:08.678338105Z",
  "Name": "package-checkbox-provider-tpm2"
 },
 {
  "Status": "success",
  "Time": "2025-12-29T00:11:07Z",
  "Name": "package-libpam-ssh"
 },
 {
  "Status": "success",
  "Time": "2025-12-29T00:36:56Z",
  "Name": "package-aws-kms-pkcs11"
 },
 {
  "Status": "success",
  "Time": "2025-12-29T00:03:04Z",
  "Name": "package-sshguard"
 },
 {
  "Status": "success",
  "Time": "2025-12-29T00:30:53Z",
  "Name": "package-openssh"
 },
 {
  "Status": "success",
  "Time": "2025-12-29T00:42:52Z",
  "Name": "package-linux"
 },
 {
  "Status": "success",
  "Time": "2025-12-29T00:09:47Z",
  "Name": "package-bootloader"
 },
 {
  "Status": "success",
  "Time": "2025-12-29T00:29:22Z",
  "Name": "package-google-guest-agent"
 },
 {
  "Status": "success",
  "Time": "2025-12-29T00:08:05Z",
  "Name": "package-python3.13"
 },
 {
  "Status": "success",
  "Time": "2025-12-29T00:20:35Z",
  "Name": "package-htop"
 },
 {
  "Status": "success",
  "Time": "2025-12-29T00:40:34Z",
  "Name": "package-openssl"
 },
 {
  "Status": "success",
  "Time": "2025-12-29T00:36:37Z",
  "Name": "package-ignition-legacy"
 },
 {
  "Status": "success",
  "Time": "2025-12-29T00:26:15Z",
  "Name": "package-gardenlinux-repo-manager"
 },
 {
  "Status": "success",
  "Time": "2025-12-29T00:06:30Z",
  "Name": "package-selinux-basics"
 },
 {
  "Status": "noRunFound",
  "Time": "2025-12-29T07:05:20.591963489Z",
  "Name": "package-open-vm-tools"
 },
 {
  "Status": "stale",
  "Time": "2025-10-20T00:16:12Z",
  "Name": "package-bind9"
 },
 {
  "Status": "stale",
  "Time": "2025-12-27T00:13:15Z",
  "Name": "package-frr"
 },
 {
  "Status": "success",
  "Time": "2025-12-29T00:19:10Z",
  "Name": "package-cloud-init"
 },
 {
  "Status": "success",
  "Time": "2025-12-29T00:27:31Z",
  "Name": "package-gardenlinux-selinux-module"
 },
 {
  "Status": "success",
  "Time": "2025-12-29T00:22:05Z",
  "Name": "package-oras"
 },
 {
  "Status": "success",
  "Time": "2025-12-29T00:40:07Z",
  "Name": "package-keylime-agent"
 },
 {
  "Status": "success",
  "Time": "2025-12-29T00:16:17Z",
  "Name": "package-edk2-cloud-hypervisor-gl"
 },
 {
  "Status": "workFlowNotFound",
  "Time": "2025-12-29T07:05:26.428689002Z",
  "Name": "package-checkbox-provider-resource"
 },
 {
  "Status": "success",
  "Time": "2025-12-29T00:33:59Z",
  "Name": "package-ignition"
 },
 {
  "Status": "success",
  "Time": "2025-12-29T00:13:31Z",
  "Name": "package-sops"
 },
 {
  "Status": "success",
  "Time": "2025-12-29T00:26:38Z",
  "Name": "package-krb5"
 },
 {
  "Status": "success",
  "Time": "2025-12-29T00:36:52Z",
  "Name": "package-expat"
 },
 {
  "Status": "success",
  "Time": "2025-12-29T00:34:35Z",
  "Name": "package-libsepol2"
 },
 {
  "Status": "success",
  "Time": "2025-12-29T00:32:27Z",
  "Name": "package-cloud-hypervisor-gl"
 },
 {
  "Status": "failure",
  "Time": "2025-12-18T00:25:28Z",
  "Name": "package-ffmpeg"
 },
 {
  "Status": "success",
  "Time": "2025-12-29T00:09:24Z",
  "Name": "package-gnutls"
 },
 {
  "Status": "success",
  "Time": "2025-12-29T00:37:06Z",
  "Name": "package-runc"
 },
 {
  "Status": "success",
  "Time": "2025-12-29T00:31:51Z",
  "Name": "package-zero-copy-initrd"
 },
 {
  "Status": "workFlowNotFound",
  "Time": "2025-12-29T07:05:36.033340705Z",
  "Name": "package-checkbox-provider-gpgpu"
 },
 {
  "Status": "success",
  "Time": "2025-12-29T00:32:18Z",
  "Name": "package-iproute2"
 },
 {
  "Status": "success",
  "Time": "2025-12-29T00:31:17Z",
  "Name": "package-golang"
 },
 {
  "Status": "success",
  "Time": "2025-12-29T00:06:07Z",
  "Name": "package-libguestfs"
 },
 {
  "Status": "success",
  "Time": "2025-12-29T00:19:24Z",
  "Name": "package-libpcap"
 },
 {
  "Status": "success",
  "Time": "2025-12-29T00:25:01Z",
  "Name": "package-htop-dev"
 },
 {
  "Status": "stale",
  "Time": "2025-12-28T00:32:34Z",
  "Name": "package-refpolicy"
 },
 {
  "Status": "success",
  "Time": "2025-12-29T00:41:14Z",
  "Name": "package-aws-sdk-cpp"
 },
 {
  "Status": "failure",
  "Time": "2025-03-10T12:46:08Z",
  "Name": "package-efitools"
 },
 {
  "Status": "success",
  "Time": "2025-12-29T00:29:08Z",
  "Name": "package-datefudge"
 },
 {
  "Status": "success",
  "Time": "2025-12-29T00:12:59Z",
  "Name": "package-resizefat32"
 },
 {
  "Status": "success",
  "Time": "2025-12-29T00:06:30Z",
  "Name": "package-rsync"
 },
 {
  "Status": "success",
  "Time": "2025-12-29T00:26:54Z",
  "Name": "package-libcap2"
 },
 {
  "Status": "stale",
  "Time": "2025-12-27T00:14:41Z",
  "Name": "package-ovh-debian-cis"
 },
 {
  "Status": "success",
  "Time": "2025-12-29T00:03:13Z",
  "Name": "package-onmetal-image"
 },
 {
  "Status": "success",
  "Time": "2025-12-29T00:08:02Z",
  "Name": "package-pam"
 },
 {
  "Status": "success",
  "Time": "2025-12-29T00:11:37Z",
  "Name": "package-containerd"
 },
 {
  "Status": "success",
  "Time": "2025-12-29T00:27:35Z",
  "Name": "package-libxml2"
 },
 {
  "Status": "success",
  "Time": "2025-12-29T00:20:14Z",
  "Name": "package-sbsigntool"
 },
 {
  "Status": "workFlowNotFound",
  "Time": "2025-12-29T07:05:52.094943648Z",
  "Name": "package-checkbox-ng"
 },
 {
  "Status": "success",
  "Time": "2025-12-29T00:35:21Z",
  "Name": "package-golang-github-checkpoint-restore-go-criu-dev"
 },
 {
  "Status": "success",
  "Time": "2025-12-29T00:38:58Z",
  "Name": "package-ferm"
 },
 {
  "Status": "failure",
  "Time": "2025-01-29T00:14:21Z",
  "Name": "package-python3.11"
 },
 {
  "Status": "success",
  "Time": "2025-12-29T00:42:18Z",
  "Name": "package-curl"
 },
 {
  "Status": "stale",
  "Time": "2025-02-11T00:22:22Z",
  "Name": "package-python3.12"
 },
 {
  "Status": "success",
  "Time": "2025-12-29T00:39:55Z",
  "Name": "package-glvd"
 },
 {
  "Status": "success",
  "Time": "2025-12-29T00:25:21Z",
  "Name": "package-jinja2"
 },
 {
  "Status": "workFlowNotFound",
  "Time": "2025-12-29T07:05:58.313420177Z",
  "Name": "package-checkbox-base"
 },
 {
  "Status": "success",
  "Time": "2025-12-29T00:34:21Z",
  "Name": "package-systemd"
 },
 {
  "Status": "success",
  "Time": "2025-12-29T00:01:52Z",
  "Name": "package-perl"
 },
 {
  "Status": "success",
  "Time": "2025-12-29T00:21:30Z",
  "Name": "package-golang-github-containers-libhvee"
 },
 {
  "Status": "success",
  "Time": "2025-12-29T00:41:57Z",
  "Name": "package-google-compute-engine"
 },
 {
  "Status": "success",
  "Time": "2025-12-29T00:31:26Z",
  "Name": "package-libgcrypt"
 }
]